bingwall/__init__.py
bingwall-2.0.0.dist-info/LICENSE
bingwall-2.0.0.dist-info/METADATA
bingwall-2.0.0.dist-info/WHEEL
bingwall-2.0.0.dist-info/top_level.txt
bingwall-2.0.0.dist-info/RECORD
