Metadata-Version: 2.1
Name: bingwall
Version: 2.0.0
Summary: a simple script to download bing wallpaper.
Home-page: https://github.com/shabane/bingwall
Author: Mohamad Shabane
Author-email: m.mohamadshabane@gmail.com
License: UNKNOWN
Project-URL: Bug Tracker, https://t.me/m_shabane
Platform: UNKNOWN
Classifier: Programming Language :: Python :: 3
Classifier: License :: OSI Approved :: MIT License
Classifier: Operating System :: OS Independent
Requires-Python: >=3
